<?xml version="1.0" encoding="utf-8"?>
<Pump xmlns:xsi="http://www.w3.org/2001/XMLSchema-instance" xmlns:xsd="http://www.w3.org/2001/XMLSchema">
  <Modell>BADU Magic II/8</Modell>
  <Manufacturer>SPECK Pumpen Verkaufsgesellschaft GmbH</Manufacturer>
  <NominalQ>8</NominalQ>
  <NominalH>8</NominalH>
  <PowerOutput>0.4</PowerOutput>
  <Author>Elias Ruemmler</Author>
  <AuthorEmail>pool@100prznt.de</AuthorEmail>
  <PerformanceCurve>
    <Ipp>
      <H>13.9724358974359</H>
      <Q>0</Q>
    </Ipp>
    <Ipp>
      <H>13.96389679318024</H>
      <Q>0.22448979591836735</Q>
    </Ipp>
    <Ipp>
      <H>13.939949488504817</H>
      <Q>0.44897959183673469</Q>
    </Ipp>
    <Ipp>
      <H>13.901603795696364</H>
      <Q>0.673469387755102</Q>
    </Ipp>
    <Ipp>
      <H>13.849819354184215</H>
      <Q>0.89795918367346939</Q>
    </Ipp>
    <Ipp>
      <H>13.785505630540316</H>
      <Q>1.1224489795918367</Q>
    </Ipp>
    <Ipp>
      <H>13.709521918479222</H>
      <Q>1.346938775510204</Q>
    </Ipp>
    <Ipp>
      <H>13.622677338858097</H>
      <Q>1.5714285714285714</Q>
    </Ipp>
    <Ipp>
      <H>13.525730839676712</H>
      <Q>1.7959183673469388</Q>
    </Ipp>
    <Ipp>
      <H>13.419391196077447</H>
      <Q>2.0204081632653059</Q>
    </Ipp>
    <Ipp>
      <H>13.304317010345292</H>
      <Q>2.2448979591836733</Q>
    </Ipp>
    <Ipp>
      <H>13.181116711907848</H>
      <Q>2.4693877551020407</Q>
    </Ipp>
    <Ipp>
      <H>13.050348557335319</H>
      <Q>2.693877551020408</Q>
    </Ipp>
    <Ipp>
      <H>12.912520630340524</H>
      <Q>2.9183673469387754</Q>
    </Ipp>
    <Ipp>
      <H>12.768090841778887</H>
      <Q>3.1428571428571428</Q>
    </Ipp>
    <Ipp>
      <H>12.61746692964844</H>
      <Q>3.36734693877551</Q>
    </Ipp>
    <Ipp>
      <H>12.46100645908983</H>
      <Q>3.5918367346938775</Q>
    </Ipp>
    <Ipp>
      <H>12.299016822386305</H>
      <Q>3.8163265306122449</Q>
    </Ipp>
    <Ipp>
      <H>12.131755238963725</H>
      <Q>4.0408163265306118</Q>
    </Ipp>
    <Ipp>
      <H>11.959428755390562</H>
      <Q>4.26530612244898</Q>
    </Ipp>
    <Ipp>
      <H>11.782194245377891</H>
      <Q>4.4897959183673466</Q>
    </Ipp>
    <Ipp>
      <H>11.6001584097794</H>
      <Q>4.7142857142857144</Q>
    </Ipp>
    <Ipp>
      <H>11.413377776591384</H>
      <Q>4.9387755102040813</Q>
    </Ipp>
    <Ipp>
      <H>11.221858700952748</H>
      <Q>5.1632653061224492</Q>
    </Ipp>
    <Ipp>
      <H>11.025557365145005</H>
      <Q>5.3877551020408161</Q>
    </Ipp>
    <Ipp>
      <H>10.824379778592277</H>
      <Q>5.6122448979591839</Q>
    </Ipp>
    <Ipp>
      <H>10.618181777861295</H>
      <Q>5.8367346938775508</Q>
    </Ipp>
    <Ipp>
      <H>10.406769026661397</H>
      <Q>6.0612244897959187</Q>
    </Ipp>
    <Ipp>
      <H>10.189897015844537</H>
      <Q>6.2857142857142856</Q>
    </Ipp>
    <Ipp>
      <H>9.9672710634052635</H>
      <Q>6.5102040816326534</Q>
    </Ipp>
    <Ipp>
      <H>9.738546314480752</H>
      <Q>6.73469387755102</Q>
    </Ipp>
    <Ipp>
      <H>9.50332774135077</H>
      <Q>6.9591836734693882</Q>
    </Ipp>
    <Ipp>
      <H>9.2611701434377061</H>
      <Q>7.1836734693877551</Q>
    </Ipp>
    <Ipp>
      <H>9.01157814730655</H>
      <Q>7.408163265306122</Q>
    </Ipp>
    <Ipp>
      <H>8.7540062066649</H>
      <Q>7.63265306122449</Q>
    </Ipp>
    <Ipp>
      <H>8.4878586023629765</H>
      <Q>7.8571428571428568</Q>
    </Ipp>
    <Ipp>
      <H>8.21248944239359</H>
      <Q>8.0816326530612237</Q>
    </Ipp>
    <Ipp>
      <H>7.927202661892168</H>
      <Q>8.3061224489795915</Q>
    </Ipp>
    <Ipp>
      <H>7.631252023136752</H>
      <Q>8.53061224489796</Q>
    </Ipp>
    <Ipp>
      <H>7.3238411155479834</H>
      <Q>8.7551020408163271</Q>
    </Ipp>
    <Ipp>
      <H>7.0041233556891234</H>
      <Q>8.9795918367346932</Q>
    </Ipp>
    <Ipp>
      <H>6.6712019872660253</H>
      <Q>9.204081632653061</Q>
    </Ipp>
    <Ipp>
      <H>6.3241300811271666</H>
      <Q>9.4285714285714288</Q>
    </Ipp>
    <Ipp>
      <H>5.9619105352636268</H>
      <Q>9.6530612244897966</Q>
    </Ipp>
    <Ipp>
      <H>5.5834960748091</H>
      <Q>9.8775510204081627</Q>
    </Ipp>
    <Ipp>
      <H>5.1877892520398774</H>
      <Q>10.102040816326531</Q>
    </Ipp>
    <Ipp>
      <H>4.7736424463748683</H>
      <Q>10.326530612244898</Q>
    </Ipp>
    <Ipp>
      <H>4.33985786437559</H>
      <Q>10.551020408163266</Q>
    </Ipp>
    <Ipp>
      <H>3.8851875397461715</H>
      <Q>10.775510204081632</Q>
    </Ipp>
    <Ipp>
      <H>3.4083333333333385</H>
      <Q>11</Q>
    </Ipp>
  </PerformanceCurve>
</Pump>